cicd/cli.py
cicd/core/action.py
cicd/core/cli.py
cicd/core/client.py
cicd/core/env.py
cicd/core/logger.py
cicd/core/typing.py
cicd/core/version.py
cicd/core/_cli/opts.py
cicd/core/cipher/cipher.py
cicd/core/cipher/cli.py
cicd/core/mixin/core.py
cicd/core/mixin/git.py
cicd/core/mixin/logger.py
cicd/core/mixin/provider.py
cicd/core/mixin/step.py
cicd/core/provider/client.py
cicd/core/provider/info.py
cicd/core/provider/models/api.py
cicd/core/provider/models/base.py
cicd/core/provider/models/pr.py
cicd/core/provider/models/project.py
cicd/core/security/keychain.py
cicd/core/syntax/data_represented.py
cicd/core/syntax/json.py
cicd/core/syntax/yaml.py
cicd/core/utils/cli_group.py
cicd/core/utils/file.py
cicd/core/utils/sh.py
cicd/core/utils/step.py
cicd/core/utils/timeout.py
cicd/ios/cli.py
cicd/ios/actions/base.py
cicd/ios/actions/cov.py
cicd/ios/actions/test_extraction.py
cicd/ios/actions/xcodebuild/__init__.py
cicd/ios/actions/xcodebuild/archive.py
cicd/ios/actions/xcodebuild/base.py
cicd/ios/actions/xcodebuild/build.py
cicd/ios/actions/xcodebuild/test.py
cicd/ios/codesign/cert.py
cicd/ios/codesign/cli.py
cicd/ios/codesign/codesign.py
cicd/ios/codesign/profile.py
cicd/ios/cov/__init__.py
cicd/ios/cov/config.py
cicd/ios/cov/cov.py
cicd/ios/cov/report.py
cicd/ios/mixin/archive.py
cicd/ios/mixin/base_ios.py
cicd/ios/mixin/build.py
cicd/ios/mixin/cocoapods.py
cicd/ios/mixin/cov.py
cicd/ios/mixin/mono.py
cicd/ios/mixin/project.py
cicd/ios/mixin/simulator.py
cicd/ios/mixin/test.py
cicd/ios/mixin/test_sharding.py
cicd/ios/mixin/version.py
cicd/ios/project/build_settings.py
cicd/ios/project/metadata.py
cicd/ios/project/project.py
cicd/ios/runner/base.py
cicd/ios/simulator/__init__.py
cicd/ios/simulator/simulator.py
cicd/ios/syntax/__init__.py
cicd/ios/syntax/xcresult.py
cicd/providers/__init__.py
cicd/providers/github/__init__.py
cicd/providers/github/client.py
cicd/providers/github/env.py
cicd/providers/gitlab/__init__.py
cicd/providers/gitlab/client.py
seeeye-0.1.1.dist-info/LICENSE
seeeye-0.1.1.dist-info/METADATA
seeeye-0.1.1.dist-info/WHEEL
seeeye-0.1.1.dist-info/entry_points.txt
seeeye-0.1.1.dist-info/top_level.txt
seeeye-0.1.1.dist-info/RECORD
