Metadata-Version: 2.1
Name: seeeye
Version: 0.1.1
Summary: CI/CD toolkits for mobile apps
Author-email: Thuyen Trinh <trinhngocthuyen@gmail.com>
License: MIT
Project-URL: Homepage, https://github.com/trinhngocthuyen/seeeye
Keywords: ci,cd,ci/cd,mobile,ios
Classifier: License :: OSI Approved :: MIT License
Classifier: Programming Language :: Python
Classifier: Programming Language :: Python :: 3
Classifier: Programming Language :: Python :: 3.10
Requires-Python: >=3.10
License-File: LICENSE
Requires-Dist: colorlog
Requires-Dist: retry
Requires-Dist: PyYAML
Requires-Dist: click
Requires-Dist: GitPython
Requires-Dist: requests
Requires-Dist: packaging
Requires-Dist: pydantic
Requires-Dist: cryptography
Provides-Extra: dev
Requires-Dist: setuptools>=61.0.0; extra == "dev"
Requires-Dist: pip-tools; extra == "dev"
Requires-Dist: black; extra == "dev"
Requires-Dist: autoflake; extra == "dev"
Requires-Dist: isort; extra == "dev"
Requires-Dist: pre-commit; extra == "dev"
Requires-Dist: bumpver; extra == "dev"
Requires-Dist: twine; extra == "dev"
Requires-Dist: pytest; extra == "dev"
Requires-Dist: pytest-cov; extra == "dev"
Requires-Dist: sphinx-rtd-theme; extra == "dev"
